prettyfi/__init__.py
prettyfi/config.py
prettyfi/exceptions.py
prettyfi/main.py
prettyfi-0.1.13.dist-info/entry_points.txt
prettyfi-0.1.13.dist-info/WHEEL
prettyfi-0.1.13.dist-info/METADATA
prettyfi-0.1.13.dist-info/RECORD
