Metadata-Version: 2.1
Name: prettyfi
Version: 0.1.13
Summary: Simple tool to prettify your files
Home-page: https://github.com/s3rius/prettyfi
Keywords: Files,Pretty,Tool,CodeStyle
Author: Pavel Kirilin
Author-email: win10@list.ru
Requires-Python: >=3.9,<4.0
Classifier: Programming Language :: Python :: 3
Classifier: Programming Language :: Python :: 3.8
Classifier: Programming Language :: Python :: 3.9
Classifier: Topic :: Utilities
Requires-Dist: pydantic (>=1.7.3,<2.0.0)
Project-URL: Repository, https://github.com/s3rius/prettyfi
